spect/__init__.py
spect/spect.py
spect-0.3.dist-info/METADATA
spect-0.3.dist-info/WHEEL
spect-0.3.dist-info/top_level.txt
spect-0.3.dist-info/zip-safe
spect-0.3.dist-info/RECORD
