Metadata-Version: 2.1
Name: spect
Version: 0.3
Summary: Categorize the `dir()` of a python object.
Home-page: https://github.com/con-f-use/spect
Author: con-f-use
Author-email: con-f-use@gmx.net
License: UNKNOWN
Platform: UNKNOWN
Classifier: Intended Audience :: Developers
Classifier: Operating System :: OS Independent
Classifier: Programming Language :: Python
